yandeley/__init__.py
yandeley/auth.py
yandeley/exception.py
yandeley/models.py
yandeley/pagination.py
yandeley/response.py
yandeley/session.py
yandeley/version.py
yandeley/models/__init__.py
yandeley/models/annotations.py
yandeley/models/base_documents.py
yandeley/models/catalog.py
yandeley/models/common.py
yandeley/models/documents.py
yandeley/models/files.py
yandeley/models/groups.py
yandeley/models/profiles.py
yandeley/resources/__init__.py
yandeley/resources/annotations.py
yandeley/resources/base.py
yandeley/resources/base_documents.py
yandeley/resources/catalog.py
yandeley/resources/documents.py
yandeley/resources/files.py
yandeley/resources/groups.py
yandeley/resources/profiles.py
yandeley/resources/trash.py
yandeley-0.4.2.dist-info/LICENSE
yandeley-0.4.2.dist-info/METADATA
yandeley-0.4.2.dist-info/WHEEL
yandeley-0.4.2.dist-info/top_level.txt
yandeley-0.4.2.dist-info/RECORD
