Metadata-Version: 2.1
Name: yandeley
Version: 0.4.2
Summary: (Yet Another) Python SDK for the Mendeley API
Home-page: https://github.com/shuichiro-makigaki/yandeley-python-sdk
Author: Shuichiro MAKIGAKI
Author-email: shuichiro.makigaki@gmail.com
License: Apache
Platform: UNKNOWN
Classifier: Development Status :: 4 - Beta
Classifier: Intended Audience :: Developers
Classifier: License :: OSI Approved :: Apache Software License
Classifier: Operating System :: OS Independent
Classifier: Programming Language :: Python
Classifier: Programming Language :: Python :: 3
Classifier: Topic :: Scientific/Engineering
Classifier: Topic :: Software Development :: Libraries :: Python Modules
License-File: LICENSE
Requires-Dist: arrow (==0.5.0)
Requires-Dist: future (==0.14.3)
Requires-Dist: memoized-property (==1.0.2)
Requires-Dist: requests (==2.5.1)
Requires-Dist: requests-oauthlib (==0.4.2)
Requires-Dist: oauthlib (==0.7.2)
